Metadata-Version: 1.0
Name: prdi
Version: 1.0
Summary: Binomial and Gaussian Distributions
Home-page: UNKNOWN
Author: Adityaraj Sahu
Author-email: 119MM0944@nitrkl.ac.in
License: UNKNOWN
Platform: UNKNOWN
